tiktok_downloader_mcp/__init__.py
tiktok_downloader_mcp/config.py
tiktok_downloader_mcp/main.py
tiktok_downloader_mcp/run.py
tiktok_downloader_mcp-0.1.0.dist-info/METADATA
tiktok_downloader_mcp-0.1.0.dist-info/WHEEL
tiktok_downloader_mcp-0.1.0.dist-info/entry_points.txt
tiktok_downloader_mcp-0.1.0.dist-info/top_level.txt
tiktok_downloader_mcp-0.1.0.dist-info/RECORD
