Metadata-Version: 2.4
Name: tiktok-downloader-mcp
Version: 0.1.0
Summary: MCP server for TikTok Downloader with integrated download capabilities
Author-email: TikTok Downloader MCP <example@example.com>
License: MIT
Project-URL: Homepage, https://github.com/yourusername/tiktok-downloader-mcp
Project-URL: Bug Tracker, https://github.com/yourusername/tiktok-downloader-mcp/issues
Classifier: Programming Language :: Python :: 3
Classifier: License :: OSI Approved :: MIT License
Classifier: Operating System :: OS Independent
Requires-Python: >=3.8
Requires-Dist: fastmcp>=0.1.0
Requires-Dist: aiohttp>=3.8.0
Requires-Dist: asyncio>=3.4.3
Requires-Dist: pydantic>=2.0.0
Requires-Dist: rich>=13.0.0
Requires-Dist: PyYAML>=6.0
Requires-Dist: python-dotenv>=1.0.0
Requires-Dist: aiofiles>=23.0
Requires-Dist: aiosqlite>=0.19.0
Requires-Dist: emoji>=2.6.0
Requires-Dist: fastapi>=0.100.0
Requires-Dist: lxml>=4.9.0
Requires-Dist: qrcode>=7.4.0
Requires-Dist: uvicorn>=0.22.0
Requires-Dist: openpyxl>=3.1.0
Requires-Dist: httpx[socks]>=0.24.0
Dynamic: requires-python
